nodeconductor_digitalocean
